dpy/__init__.py
dpy-0.0.1.dist-info/WHEEL
dpy-0.0.1.dist-info/METADATA
dpy-0.0.1.dist-info/RECORD
